.gitignore
MANIFEST.in
setup.py
docs/CREDITS.TXT
docs/INSTALL.txt
docs/LICENSE.GPL
docs/LICENSE.txt
docs/TODO.txt
plonehrm/__init__.py
plonehrm.contracts.egg-info/PKG-INFO
plonehrm.contracts.egg-info/SOURCES.txt
plonehrm.contracts.egg-info/dependency_links.txt
plonehrm.contracts.egg-info/entry_points.txt
plonehrm.contracts.egg-info/namespace_packages.txt
plonehrm.contracts.egg-info/not-zip-safe
plonehrm.contracts.egg-info/requires.txt
plonehrm.contracts.egg-info/top_level.txt
plonehrm/contracts/HISTORY.txt
plonehrm/contracts/README.txt
plonehrm/contracts/__init__.py
plonehrm/contracts/config.py
plonehrm/contracts/configure.zcml
plonehrm/contracts/deprecation.zcml
plonehrm/contracts/events.py
plonehrm/contracts/interfaces.py
plonehrm/contracts/permissions.zcml
plonehrm/contracts/rebuild_i18n.sh
plonehrm/contracts/setuphandlers.py
plonehrm/contracts/tool.gif
plonehrm/contracts/validators.py
plonehrm/contracts/content/__init__.py
plonehrm/contracts/content/contract.py
plonehrm/contracts/content/letter.py
plonehrm/contracts/content/tool.py
plonehrm/contracts/doc/TODO.txt
plonehrm/contracts/doc/checkers.txt
plonehrm/contracts/doc/contracts-technical.txt
plonehrm/contracts/locales/contract.pot
plonehrm/contracts/locales/en/LC_MESSAGES/contract.po
plonehrm/contracts/locales/nl/LC_MESSAGES/contract.po
plonehrm/contracts/locales/pt_BR/LC_MESSAGES/contract.po
plonehrm/contracts/notifications/__init__.py
plonehrm/contracts/notifications/checkers.py
plonehrm/contracts/notifications/configure.zcml
plonehrm/contracts/notifications/contract_nears_ending.pt
plonehrm/contracts/notifications/events.py
plonehrm/contracts/notifications/fixed_contract_nears_ending.pt
plonehrm/contracts/notifications/interfaces.py
plonehrm/contracts/notifications/no_current_contract.pt
plonehrm/contracts/notifications/trial_nears_ending.pt
plonehrm/contracts/profiles/default/actionicons.xml
plonehrm/contracts/profiles/default/controlpanel.xml
plonehrm/contracts/profiles/default/cssregistry.xml
plonehrm/contracts/profiles/default/factorytool.xml
plonehrm/contracts/profiles/default/plonehrm.contracts.txt
plonehrm/contracts/profiles/default/propertiestool.xml
plonehrm/contracts/profiles/default/rolemap.xml
plonehrm/contracts/profiles/default/toolset.xml
plonehrm/contracts/profiles/default/types.xml
