Metadata-Version: 1.1
Name: plonehrm.contracts
Version: 3.10
Summary: Contracts for Plone HRM
Home-page: https://prettigpersoneel.nl
Author: Zest Software
Author-email: info@zestsoftware.nl
License: GPL
Keywords: human resource management contracts
Platform: UNKNOWN
Classifier: Framework :: Plone
Classifier: Framework :: Plone :: 3.3
Classifier: Framework :: Zope2
Classifier: Framework :: Zope3
Classifier: Programming Language :: Python
Classifier: Programming Language :: Python :: 2.4
Classifier: Topic :: Software Development :: Libraries :: Python Modules
